vidconcept_sum/__init__.py
vidconcept_sum/main.py
vidconcept_sum/prompts.py
vidconcept_sum-2025.12.21193338.dist-info/METADATA
vidconcept_sum-2025.12.21193338.dist-info/WHEEL
vidconcept_sum-2025.12.21193338.dist-info/top_level.txt
vidconcept_sum-2025.12.21193338.dist-info/RECORD
