Metadata-Version: 2.4
Name: vidconcept-sum
Version: 2025.12.21193338
Summary: vidconcept-sum generates structured, factual summaries of scientific/educational concepts from video titles or descriptions using an LLM.
Author-email: vidconcept-sum <hi@eugene.plus>
License: MIT
Project-URL: Homepage, https://github.com/chigwell/vidconcept-sum
Requires-Python: >=3.9
Requires-Dist: langchain-llm7>=0.0.0
Requires-Dist: llmatch-messages>=0.0.0
Requires-Dist: langchain-core>=0.3.0
